{
  "$schema": "https://tree-sitter.github.io/tree-sitter/assets/schemas/grammar.schema.json",
  "name": "lume",
  "word": "identifier",
  "rules": {
    "source_file": {
      "type": "REPEAT",
      "content": {
        "type": "CHOICE",
        "members": [
          {
            "type": "SYMBOL",
            "name": "_definition"
          },
          {
            "type": "PATTERN",
            "value": "\\r?\\n"
          }
        ]
      }
    },
    "_definition": {
      "type": "CHOICE",
      "members": [
        {
          "type": "SYMBOL",
          "name": "import_statement"
        },
        {
          "type": "SYMBOL",
          "name": "publish_statement"
        },
        {
          "type": "SYMBOL",
          "name": "enum_declaration"
        },
        {
          "type": "SYMBOL",
          "name": "struct_declaration"
        },
        {
          "type": "SYMBOL",
          "name": "const_declaration"
        },
        {
          "type": "SYMBOL",
          "name": "fn_declaration"
        },
        {
          "type": "SYMBOL",
          "name": "mutable_declaration"
        },
        {
          "type": "SYMBOL",
          "name": "future_keyword"
        },
        {
          "type": "SYMBOL",
          "name": "future_operator"
        },
        {
          "type": "SYMBOL",
          "name": "visibility"
        },
        {
          "type": "SYMBOL",
          "name": "_attribute_like"
        }
      ]
    },
    "_attribute_like": {
      "type": "CHOICE",
      "members": [
        {
          "type": "SYMBOL",
          "name": "attribute"
        },
        {
          "type": "SYMBOL",
          "name": "builtin_attribute"
        }
      ]
    },
    "import_statement": {
      "type": "PREC_RIGHT",
      "value": 0,
      "content": {
        "type": "SEQ",
        "members": [
          {
            "type": "STRING",
            "value": "import"
          },
          {
            "type": "FIELD",
            "name": "path",
            "content": {
              "type": "SYMBOL",
              "name": "import_path"
            }
          },
          {
            "type": "CHOICE",
            "members": [
              {
                "type": "SEQ",
                "members": [
                  {
                    "type": "STRING",
                    "value": "::"
                  },
                  {
                    "type": "CHOICE",
                    "members": [
                      {
                        "type": "SEQ",
                        "members": [
                          {
                            "type": "STRING",
                            "value": "{"
                          },
                          {
                            "type": "REPEAT",
                            "content": {
                              "type": "CHOICE",
                              "members": [
                                {
                                  "type": "SYMBOL",
                                  "name": "_imported_item"
                                },
                                {
                                  "type": "STRING",
                                  "value": ","
                                },
                                {
                                  "type": "PATTERN",
                                  "value": "\\r?\\n"
                                }
                              ]
                            }
                          },
                          {
                            "type": "CHOICE",
                            "members": [
                              {
                                "type": "STRING",
                                "value": "}"
                              },
                              {
                                "type": "BLANK"
                              }
                            ]
                          }
                        ]
                      },
                      {
                        "type": "BLANK"
                      }
                    ]
                  }
                ]
              },
              {
                "type": "BLANK"
              }
            ]
          }
        ]
      }
    },
    "publish_statement": {
      "type": "PREC_RIGHT",
      "value": 0,
      "content": {
        "type": "SEQ",
        "members": [
          {
            "type": "STRING",
            "value": "publish"
          },
          {
            "type": "FIELD",
            "name": "path",
            "content": {
              "type": "SYMBOL",
              "name": "import_path"
            }
          },
          {
            "type": "CHOICE",
            "members": [
              {
                "type": "SEQ",
                "members": [
                  {
                    "type": "STRING",
                    "value": "::"
                  },
                  {
                    "type": "CHOICE",
                    "members": [
                      {
                        "type": "SEQ",
                        "members": [
                          {
                            "type": "STRING",
                            "value": "{"
                          },
                          {
                            "type": "REPEAT",
                            "content": {
                              "type": "CHOICE",
                              "members": [
                                {
                                  "type": "SYMBOL",
                                  "name": "_imported_item"
                                },
                                {
                                  "type": "STRING",
                                  "value": ","
                                },
                                {
                                  "type": "PATTERN",
                                  "value": "\\r?\\n"
                                }
                              ]
                            }
                          },
                          {
                            "type": "CHOICE",
                            "members": [
                              {
                                "type": "STRING",
                                "value": "}"
                              },
                              {
                                "type": "BLANK"
                              }
                            ]
                          }
                        ]
                      },
                      {
                        "type": "BLANK"
                      }
                    ]
                  }
                ]
              },
              {
                "type": "BLANK"
              }
            ]
          }
        ]
      }
    },
    "_imported_item": {
      "type": "CHOICE",
      "members": [
        {
          "type": "ALIAS",
          "content": {
            "type": "SYMBOL",
            "name": "identifier"
          },
          "named": true,
          "value": "imported_name"
        },
        {
          "type": "SYMBOL",
          "name": "imported_attribute_namespace"
        }
      ]
    },
    "imported_attribute_namespace": {
      "type": "SEQ",
      "members": [
        {
          "type": "STRING",
          "value": "#"
        },
        {
          "type": "FIELD",
          "name": "name",
          "content": {
            "type": "SYMBOL",
            "name": "attribute_name"
          }
        }
      ]
    },
    "visibility": {
      "type": "CHOICE",
      "members": [
        {
          "type": "STRING",
          "value": "pub"
        },
        {
          "type": "STRING",
          "value": "publish"
        }
      ]
    },
    "const_declaration": {
      "type": "PREC_RIGHT",
      "value": 0,
      "content": {
        "type": "SEQ",
        "members": [
          {
            "type": "CHOICE",
            "members": [
              {
                "type": "SYMBOL",
                "name": "visibility"
              },
              {
                "type": "BLANK"
              }
            ]
          },
          {
            "type": "STRING",
            "value": "const"
          }
        ]
      }
    },
    "fn_declaration": {
      "type": "PREC_RIGHT",
      "value": 0,
      "content": {
        "type": "SEQ",
        "members": [
          {
            "type": "CHOICE",
            "members": [
              {
                "type": "SYMBOL",
                "name": "visibility"
              },
              {
                "type": "BLANK"
              }
            ]
          },
          {
            "type": "STRING",
            "value": "fn"
          }
        ]
      }
    },
    "mutable_declaration": {
      "type": "PREC_RIGHT",
      "value": 0,
      "content": {
        "type": "SEQ",
        "members": [
          {
            "type": "CHOICE",
            "members": [
              {
                "type": "SYMBOL",
                "name": "visibility"
              },
              {
                "type": "BLANK"
              }
            ]
          },
          {
            "type": "STRING",
            "value": "mutable"
          }
        ]
      }
    },
    "future_keyword": {
      "type": "CHOICE",
      "members": [
        {
          "type": "STRING",
          "value": "if"
        },
        {
          "type": "STRING",
          "value": "otherwise"
        },
        {
          "type": "STRING",
          "value": "return"
        },
        {
          "type": "STRING",
          "value": "match"
        },
        {
          "type": "STRING",
          "value": "when"
        },
        {
          "type": "STRING",
          "value": "else"
        },
        {
          "type": "STRING",
          "value": "for"
        },
        {
          "type": "STRING",
          "value": "each"
        },
        {
          "type": "STRING",
          "value": "in"
        },
        {
          "type": "STRING",
          "value": "component"
        },
        {
          "type": "STRING",
          "value": "repeat"
        },
        {
          "type": "STRING",
          "value": "while"
        },
        {
          "type": "STRING",
          "value": "until"
        }
      ]
    },
    "future_operator": {
      "type": "CHOICE",
      "members": [
        {
          "type": "STRING",
          "value": "-->"
        },
        {
          "type": "STRING",
          "value": ">>"
        },
        {
          "type": "STRING",
          "value": "..."
        }
      ]
    },
    "import_path": {
      "type": "CHOICE",
      "members": [
        {
          "type": "SEQ",
          "members": [
            {
              "type": "SYMBOL",
              "name": "path_alias_prefix"
            },
            {
              "type": "CHOICE",
              "members": [
                {
                  "type": "SYMBOL",
                  "name": "path_body"
                },
                {
                  "type": "BLANK"
                }
              ]
            }
          ]
        },
        {
          "type": "SEQ",
          "members": [
            {
              "type": "SYMBOL",
              "name": "path_relative_prefix"
            },
            {
              "type": "CHOICE",
              "members": [
                {
                  "type": "SYMBOL",
                  "name": "path_body"
                },
                {
                  "type": "BLANK"
                }
              ]
            }
          ]
        },
        {
          "type": "SYMBOL",
          "name": "path_body"
        }
      ]
    },
    "path_alias_prefix": {
      "type": "STRING",
      "value": "#"
    },
    "path_relative_prefix": {
      "type": "PATTERN",
      "value": "\\.\\.?"
    },
    "path_body": {
      "type": "CHOICE",
      "members": [
        {
          "type": "SEQ",
          "members": [
            {
              "type": "STRING",
              "value": "/"
            },
            {
              "type": "CHOICE",
              "members": [
                {
                  "type": "SEQ",
                  "members": [
                    {
                      "type": "SYMBOL",
                      "name": "path_segment"
                    },
                    {
                      "type": "REPEAT",
                      "content": {
                        "type": "SEQ",
                        "members": [
                          {
                            "type": "STRING",
                            "value": "/"
                          },
                          {
                            "type": "CHOICE",
                            "members": [
                              {
                                "type": "SYMBOL",
                                "name": "path_segment"
                              },
                              {
                                "type": "BLANK"
                              }
                            ]
                          }
                        ]
                      }
                    }
                  ]
                },
                {
                  "type": "BLANK"
                }
              ]
            }
          ]
        },
        {
          "type": "SEQ",
          "members": [
            {
              "type": "SYMBOL",
              "name": "path_segment"
            },
            {
              "type": "REPEAT",
              "content": {
                "type": "SEQ",
                "members": [
                  {
                    "type": "STRING",
                    "value": "/"
                  },
                  {
                    "type": "CHOICE",
                    "members": [
                      {
                        "type": "SYMBOL",
                        "name": "path_segment"
                      },
                      {
                        "type": "BLANK"
                      }
                    ]
                  }
                ]
              }
            }
          ]
        }
      ]
    },
    "path_segment": {
      "type": "PATTERN",
      "value": "[\\w@][\\w\\-.@]*"
    },
    "enum_declaration": {
      "type": "SEQ",
      "members": [
        {
          "type": "CHOICE",
          "members": [
            {
              "type": "SYMBOL",
              "name": "visibility"
            },
            {
              "type": "BLANK"
            }
          ]
        },
        {
          "type": "STRING",
          "value": "enum"
        },
        {
          "type": "CHOICE",
          "members": [
            {
              "type": "FIELD",
              "name": "name",
              "content": {
                "type": "SYMBOL",
                "name": "type_identifier"
              }
            },
            {
              "type": "BLANK"
            }
          ]
        },
        {
          "type": "CHOICE",
          "members": [
            {
              "type": "SYMBOL",
              "name": "enum_body"
            },
            {
              "type": "BLANK"
            }
          ]
        }
      ]
    },
    "enum_body": {
      "type": "PREC_RIGHT",
      "value": 0,
      "content": {
        "type": "SEQ",
        "members": [
          {
            "type": "STRING",
            "value": "{"
          },
          {
            "type": "REPEAT",
            "content": {
              "type": "CHOICE",
              "members": [
                {
                  "type": "SYMBOL",
                  "name": "variant"
                },
                {
                  "type": "SYMBOL",
                  "name": "_attribute_like"
                },
                {
                  "type": "PATTERN",
                  "value": "\\r?\\n"
                }
              ]
            }
          },
          {
            "type": "CHOICE",
            "members": [
              {
                "type": "STRING",
                "value": "}"
              },
              {
                "type": "BLANK"
              }
            ]
          }
        ]
      }
    },
    "variant": {
      "type": "PREC_RIGHT",
      "value": 0,
      "content": {
        "type": "SEQ",
        "members": [
          {
            "type": "STRING",
            "value": "|"
          },
          {
            "type": "FIELD",
            "name": "name",
            "content": {
              "type": "SYMBOL",
              "name": "type_identifier"
            }
          },
          {
            "type": "CHOICE",
            "members": [
              {
                "type": "SYMBOL",
                "name": "variant_params"
              },
              {
                "type": "BLANK"
              }
            ]
          },
          {
            "type": "CHOICE",
            "members": [
              {
                "type": "SYMBOL",
                "name": "_attribute_like"
              },
              {
                "type": "BLANK"
              }
            ]
          },
          {
            "type": "CHOICE",
            "members": [
              {
                "type": "STRING",
                "value": ","
              },
              {
                "type": "BLANK"
              }
            ]
          }
        ]
      }
    },
    "variant_params": {
      "type": "SEQ",
      "members": [
        {
          "type": "STRING",
          "value": "{"
        },
        {
          "type": "CHOICE",
          "members": [
            {
              "type": "SEQ",
              "members": [
                {
                  "type": "CHOICE",
                  "members": [
                    {
                      "type": "SYMBOL",
                      "name": "spread_type"
                    },
                    {
                      "type": "SYMBOL",
                      "name": "named_field"
                    },
                    {
                      "type": "SYMBOL",
                      "name": "_type"
                    }
                  ]
                },
                {
                  "type": "REPEAT",
                  "content": {
                    "type": "SEQ",
                    "members": [
                      {
                        "type": "STRING",
                        "value": ","
                      },
                      {
                        "type": "CHOICE",
                        "members": [
                          {
                            "type": "SYMBOL",
                            "name": "spread_type"
                          },
                          {
                            "type": "SYMBOL",
                            "name": "named_field"
                          },
                          {
                            "type": "SYMBOL",
                            "name": "_type"
                          }
                        ]
                      }
                    ]
                  }
                }
              ]
            },
            {
              "type": "BLANK"
            }
          ]
        },
        {
          "type": "STRING",
          "value": "}"
        }
      ]
    },
    "named_field": {
      "type": "SEQ",
      "members": [
        {
          "type": "FIELD",
          "name": "name",
          "content": {
            "type": "SYMBOL",
            "name": "identifier"
          }
        },
        {
          "type": "STRING",
          "value": ":"
        },
        {
          "type": "FIELD",
          "name": "type",
          "content": {
            "type": "SYMBOL",
            "name": "_type"
          }
        }
      ]
    },
    "struct_declaration": {
      "type": "SEQ",
      "members": [
        {
          "type": "CHOICE",
          "members": [
            {
              "type": "SYMBOL",
              "name": "visibility"
            },
            {
              "type": "BLANK"
            }
          ]
        },
        {
          "type": "STRING",
          "value": "struct"
        },
        {
          "type": "CHOICE",
          "members": [
            {
              "type": "FIELD",
              "name": "name",
              "content": {
                "type": "SYMBOL",
                "name": "type_identifier"
              }
            },
            {
              "type": "BLANK"
            }
          ]
        },
        {
          "type": "CHOICE",
          "members": [
            {
              "type": "SYMBOL",
              "name": "struct_body"
            },
            {
              "type": "BLANK"
            }
          ]
        }
      ]
    },
    "struct_body": {
      "type": "PREC_RIGHT",
      "value": 0,
      "content": {
        "type": "SEQ",
        "members": [
          {
            "type": "STRING",
            "value": "{"
          },
          {
            "type": "REPEAT",
            "content": {
              "type": "CHOICE",
              "members": [
                {
                  "type": "SYMBOL",
                  "name": "struct_field"
                },
                {
                  "type": "SYMBOL",
                  "name": "spread_type"
                },
                {
                  "type": "SYMBOL",
                  "name": "_attribute_like"
                },
                {
                  "type": "STRING",
                  "value": ","
                },
                {
                  "type": "PATTERN",
                  "value": "\\r?\\n"
                }
              ]
            }
          },
          {
            "type": "CHOICE",
            "members": [
              {
                "type": "STRING",
                "value": "}"
              },
              {
                "type": "BLANK"
              }
            ]
          }
        ]
      }
    },
    "struct_field": {
      "type": "PREC_RIGHT",
      "value": 0,
      "content": {
        "type": "SEQ",
        "members": [
          {
            "type": "FIELD",
            "name": "name",
            "content": {
              "type": "SYMBOL",
              "name": "identifier"
            }
          },
          {
            "type": "STRING",
            "value": ":"
          },
          {
            "type": "FIELD",
            "name": "type",
            "content": {
              "type": "SYMBOL",
              "name": "_type"
            }
          },
          {
            "type": "CHOICE",
            "members": [
              {
                "type": "SYMBOL",
                "name": "_attribute_like"
              },
              {
                "type": "BLANK"
              }
            ]
          },
          {
            "type": "CHOICE",
            "members": [
              {
                "type": "STRING",
                "value": ","
              },
              {
                "type": "BLANK"
              }
            ]
          }
        ]
      }
    },
    "_type": {
      "type": "CHOICE",
      "members": [
        {
          "type": "SYMBOL",
          "name": "maybe_type"
        },
        {
          "type": "SYMBOL",
          "name": "required_type"
        },
        {
          "type": "SYMBOL",
          "name": "generic_type"
        },
        {
          "type": "SYMBOL",
          "name": "nested_struct"
        },
        {
          "type": "SYMBOL",
          "name": "type_identifier"
        }
      ]
    },
    "maybe_type": {
      "type": "SEQ",
      "members": [
        {
          "type": "STRING",
          "value": "maybe"
        },
        {
          "type": "SYMBOL",
          "name": "_type"
        }
      ]
    },
    "required_type": {
      "type": "SEQ",
      "members": [
        {
          "type": "STRING",
          "value": "required"
        },
        {
          "type": "SYMBOL",
          "name": "_type"
        }
      ]
    },
    "generic_type": {
      "type": "SEQ",
      "members": [
        {
          "type": "FIELD",
          "name": "name",
          "content": {
            "type": "SYMBOL",
            "name": "type_identifier"
          }
        },
        {
          "type": "SYMBOL",
          "name": "type_arguments"
        }
      ]
    },
    "type_arguments": {
      "type": "SEQ",
      "members": [
        {
          "type": "STRING",
          "value": "<"
        },
        {
          "type": "CHOICE",
          "members": [
            {
              "type": "SEQ",
              "members": [
                {
                  "type": "SYMBOL",
                  "name": "_type"
                },
                {
                  "type": "REPEAT",
                  "content": {
                    "type": "SEQ",
                    "members": [
                      {
                        "type": "STRING",
                        "value": ","
                      },
                      {
                        "type": "SYMBOL",
                        "name": "_type"
                      }
                    ]
                  }
                }
              ]
            },
            {
              "type": "BLANK"
            }
          ]
        },
        {
          "type": "STRING",
          "value": ">"
        }
      ]
    },
    "nested_struct": {
      "type": "SEQ",
      "members": [
        {
          "type": "STRING",
          "value": "{"
        },
        {
          "type": "REPEAT",
          "content": {
            "type": "CHOICE",
            "members": [
              {
                "type": "SYMBOL",
                "name": "struct_field"
              },
              {
                "type": "SYMBOL",
                "name": "spread_type"
              },
              {
                "type": "SYMBOL",
                "name": "_attribute_like"
              },
              {
                "type": "STRING",
                "value": ","
              },
              {
                "type": "PATTERN",
                "value": "\\r?\\n"
              }
            ]
          }
        },
        {
          "type": "STRING",
          "value": "}"
        }
      ]
    },
    "spread_type": {
      "type": "SEQ",
      "members": [
        {
          "type": "STRING",
          "value": "..."
        },
        {
          "type": "SYMBOL",
          "name": "type_identifier"
        }
      ]
    },
    "attribute": {
      "type": "PREC_RIGHT",
      "value": 0,
      "content": {
        "type": "SEQ",
        "members": [
          {
            "type": "STRING",
            "value": "#"
          },
          {
            "type": "SYMBOL",
            "name": "attribute_name"
          },
          {
            "type": "CHOICE",
            "members": [
              {
                "type": "SYMBOL",
                "name": "attribute_arguments"
              },
              {
                "type": "BLANK"
              }
            ]
          }
        ]
      }
    },
    "builtin_attribute": {
      "type": "PREC_RIGHT",
      "value": 0,
      "content": {
        "type": "SEQ",
        "members": [
          {
            "type": "SYMBOL",
            "name": "builtin_attribute_name"
          },
          {
            "type": "CHOICE",
            "members": [
              {
                "type": "SYMBOL",
                "name": "attribute_arguments"
              },
              {
                "type": "BLANK"
              }
            ]
          }
        ]
      }
    },
    "attribute_arguments": {
      "type": "CHOICE",
      "members": [
        {
          "type": "SEQ",
          "members": [
            {
              "type": "STRING",
              "value": "("
            },
            {
              "type": "CHOICE",
              "members": [
                {
                  "type": "SEQ",
                  "members": [
                    {
                      "type": "SYMBOL",
                      "name": "attribute_value"
                    },
                    {
                      "type": "REPEAT",
                      "content": {
                        "type": "SEQ",
                        "members": [
                          {
                            "type": "STRING",
                            "value": ","
                          },
                          {
                            "type": "SYMBOL",
                            "name": "attribute_value"
                          }
                        ]
                      }
                    }
                  ]
                },
                {
                  "type": "BLANK"
                }
              ]
            },
            {
              "type": "STRING",
              "value": ")"
            }
          ]
        },
        {
          "type": "PREC_RIGHT",
          "value": 0,
          "content": {
            "type": "SEQ",
            "members": [
              {
                "type": "SYMBOL",
                "name": "attribute_value"
              },
              {
                "type": "REPEAT1",
                "content": {
                  "type": "SEQ",
                  "members": [
                    {
                      "type": "SYMBOL",
                      "name": "attribute_list_delimiter"
                    },
                    {
                      "type": "SYMBOL",
                      "name": "attribute_value"
                    }
                  ]
                }
              }
            ]
          }
        },
        {
          "type": "SYMBOL",
          "name": "inline_attribute_arguments"
        }
      ]
    },
    "inline_attribute_arguments": {
      "type": "PREC_RIGHT",
      "value": 0,
      "content": {
        "type": "CHOICE",
        "members": [
          {
            "type": "SYMBOL",
            "name": "attribute_value"
          },
          {
            "type": "SEQ",
            "members": [
              {
                "type": "SYMBOL",
                "name": "attribute_value"
              },
              {
                "type": "REPEAT1",
                "content": {
                  "type": "SEQ",
                  "members": [
                    {
                      "type": "STRING",
                      "value": "|"
                    },
                    {
                      "type": "SYMBOL",
                      "name": "attribute_value"
                    }
                  ]
                }
              }
            ]
          }
        ]
      }
    },
    "attribute_value": {
      "type": "CHOICE",
      "members": [
        {
          "type": "SYMBOL",
          "name": "string"
        },
        {
          "type": "SYMBOL",
          "name": "type_identifier"
        },
        {
          "type": "SYMBOL",
          "name": "attribute_arg"
        }
      ]
    },
    "builtin_attribute_name": {
      "type": "CHOICE",
      "members": [
        {
          "type": "STRING",
          "value": "aka"
        },
        {
          "type": "STRING",
          "value": "default"
        }
      ]
    },
    "attribute_name": {
      "type": "PATTERN",
      "value": "[a-zA-Z_][a-zA-Z0-9_-]*(?::[a-zA-Z_][a-zA-Z0-9_-]*)*"
    },
    "attribute_list_delimiter": {
      "type": "TOKEN",
      "content": {
        "type": "PATTERN",
        "value": ",[ \\t]+"
      }
    },
    "attribute_arg": {
      "type": "PATTERN",
      "value": "[a-z_][\\w\\-]*"
    },
    "comment": {
      "type": "SEQ",
      "members": [
        {
          "type": "STRING",
          "value": "//"
        },
        {
          "type": "PATTERN",
          "value": ".*"
        }
      ]
    },
    "string": {
      "type": "PATTERN",
      "value": "'[^'\\n]*'?|\"[^\"\\n]*\"?"
    },
    "type_identifier": {
      "type": "PATTERN",
      "value": "[A-Z][a-zA-Z0-9_]*"
    },
    "identifier": {
      "type": "PATTERN",
      "value": "[a-zA-Z_][a-zA-Z0-9_]*"
    }
  },
  "extras": [
    {
      "type": "PATTERN",
      "value": "[ \\t]"
    },
    {
      "type": "SYMBOL",
      "name": "comment"
    }
  ],
  "conflicts": [
    [
      "publish_statement",
      "visibility"
    ],
    [
      "_definition",
      "enum_declaration"
    ],
    [
      "_definition",
      "struct_declaration"
    ],
    [
      "_definition",
      "const_declaration"
    ],
    [
      "_definition",
      "fn_declaration"
    ],
    [
      "_definition",
      "mutable_declaration"
    ]
  ],
  "precedences": [],
  "externals": [],
  "inline": [],
  "supertypes": [],
  "reserved": {}
}